django_simple_ip_restrict/__init__.py
django_simple_ip_restrict/middleware.py
django_simple_ip_restrict-1.0.45.dist-info/METADATA
django_simple_ip_restrict-1.0.45.dist-info/WHEEL
django_simple_ip_restrict-1.0.45.dist-info/RECORD
