Metadata-Version: 2.1
Name: django-simple-ip-restrict
Version: 1.0.45
Summary: This middleware allows you to mark Django URL namespaces as unavailable to all requests except those coming from a whitelisted IP subnet.
Home-page: https://github.com/hatch-studio/django-simple-ip-restrict
Author: stitchdev
Author-email: dev@stitchdesignlab.com
Requires-Python: >=3.5,<4.0
Classifier: Development Status :: 5 - Production/Stable
Classifier: Environment :: Web Environment
Classifier: Framework :: Django
Classifier: Intended Audience :: Developers
Classifier: Operating System :: OS Independent
Classifier: Programming Language :: Python
Classifier: Programming Language :: Python :: 3
Classifier: Programming Language :: Python :: 3.5
Classifier: Programming Language :: Python :: 3.6
Classifier: Programming Language :: Python :: 3.7
Classifier: Programming Language :: Python :: 3.8
Classifier: Programming Language :: Python :: 3.9
Classifier: Programming Language :: Python :: 3.10
Classifier: Programming Language :: Python :: 3.11
Classifier: Programming Language :: Python :: 3
Classifier: Topic :: Software Development :: Libraries :: Python Modules
Requires-Dist: django (>=2.0,<5.0)
Requires-Dist: netaddr (>=0.8.0,<0.9.0)
Project-URL: Repository, https://github.com/hatch-studio/django-simple-ip-restrict
